abacusnbody/__init__.py
abacusnbody/util.py
abacusnbody/version.py
abacusnbody/analysis/cic.py
abacusnbody/analysis/power_spectrum.py
abacusnbody/analysis/shear.py
abacusnbody/analysis/tpcf_corrfunc.py
abacusnbody/analysis/tsc.py
abacusnbody/data/__init__.py
abacusnbody/data/asdf.py
abacusnbody/data/bitpacked.py
abacusnbody/data/compaso_halo_catalog.py
abacusnbody/data/pack9.py
abacusnbody/data/pipe_asdf.py
abacusnbody/data/read_abacus.py
abacusnbody/hod/GRAND_HOD.py
abacusnbody/hod/__init__.py
abacusnbody/hod/abacus_hod.py
abacusnbody/hod/menv.py
abacusnbody/hod/prepare_sim.py
abacusnbody/hod/utils.py
abacusnbody/hod/zcv/advect_fields.py
abacusnbody/hod/zcv/ic_fields.py
abacusnbody/hod/zcv/linear_fields.py
abacusnbody/hod/zcv/tools_cv.py
abacusnbody/hod/zcv/tracer_power.py
abacusnbody/hod/zcv/zenbu_window.py
abacusnbody/metadata/__init__.py
abacusnbody/metadata/abacusdesi2_headers_compressed.asdf
abacusnbody/metadata/abacussummit.py
abacusnbody/metadata/abacussummit_headers_compressed.asdf
abacusutils-2.1.2.dist-info/licenses/LICENSE
abacusutils-2.1.2.dist-info/METADATA
abacusutils-2.1.2.dist-info/WHEEL
abacusutils-2.1.2.dist-info/entry_points.txt
abacusutils-2.1.2.dist-info/top_level.txt
abacusutils-2.1.2.dist-info/RECORD
