Metadata-Version: 2.4
Name: abacusutils
Version: 2.1.2
Summary: Python code to read halo catalogs and other Abacus N-body data products
Author: Daniel Eisenstein, Philip Pinto, Nina Maksimova, Sownak Bose, Boryana Hadzhiyska, Sihan (Sandy) Yuan
Author-email: Lehman Garrison <lgarrison@flatironinstitute.org>
Project-URL: Repository, https://github.com/abacusorg/abacusutils
Classifier: Programming Language :: Python :: 3
Classifier: License :: OSI Approved :: GNU General Public License v3 (GPLv3)
Requires-Python: >=3.9
License-File: LICENSE
Requires-Dist: numpy>=1.16
Requires-Dist: blosc>=1.9.2
Requires-Dist: astropy>=4.0.0
Requires-Dist: scipy>=1.5.0
Requires-Dist: numba>=0.56
Requires-Dist: asdf>=3.1.0
Requires-Dist: h5py
Requires-Dist: pyyaml
Requires-Dist: msgpack>=1
Requires-Dist: parallel_numpy_rng>=0.1.2
Requires-Dist: asdf-astropy>=0.3
Provides-Extra: all
Requires-Dist: zenbu-fftw>=1; extra == "all"
Requires-Dist: classy; extra == "all"
Requires-Dist: Corrfunc>=2; extra == "all"
Requires-Dist: emcee; extra == "all"
Requires-Dist: schwimmbad; extra == "all"
Requires-Dist: getdist; extra == "all"
Requires-Dist: dynesty; extra == "all"
Requires-Dist: dill; extra == "all"
Requires-Dist: click; extra == "all"
Provides-Extra: docs
Requires-Dist: sphinx>=4.2; extra == "docs"
Requires-Dist: sphinx-book-theme>=0.3; extra == "docs"
Requires-Dist: myst_nb>=0.17.1; extra == "docs"
Provides-Extra: test
Requires-Dist: abacusutils[all]; extra == "test"
Requires-Dist: pytest; extra == "test"
Dynamic: license-file
